odoo/addons/account_invoice_mode_monthly/README.rst
odoo/addons/account_invoice_mode_monthly/__init__.py
odoo/addons/account_invoice_mode_monthly/__manifest__.py
odoo/addons/account_invoice_mode_monthly/data/ir_cron.xml
odoo/addons/account_invoice_mode_monthly/i18n/account_invoice_mode_monthly.pot
odoo/addons/account_invoice_mode_monthly/models/__init__.py
odoo/addons/account_invoice_mode_monthly/models/res_company.py
odoo/addons/account_invoice_mode_monthly/models/res_config_settings.py
odoo/addons/account_invoice_mode_monthly/models/res_partner.py
odoo/addons/account_invoice_mode_monthly/models/sale_order.py
odoo/addons/account_invoice_mode_monthly/readme/CONTRIBUTORS.rst
odoo/addons/account_invoice_mode_monthly/readme/DESCRIPTION.rst
odoo/addons/account_invoice_mode_monthly/readme/INSTALL.rst
odoo/addons/account_invoice_mode_monthly/readme/ROADMAP.rst
odoo/addons/account_invoice_mode_monthly/static/description/icon.png
odoo/addons/account_invoice_mode_monthly/static/description/index.html
odoo/addons/account_invoice_mode_monthly/tests/__init__.py
odoo/addons/account_invoice_mode_monthly/tests/test_invoice_mode_monthly.py
odoo/addons/account_invoice_mode_monthly/tests/test_invoice_mode_monthly_is_it_today.py
odoo/addons/account_invoice_mode_monthly/views/res_config_settings_views.xml
odoo13_addon_account_invoice_mode_monthly-13.0.1.0.1.dist-info/METADATA
odoo13_addon_account_invoice_mode_monthly-13.0.1.0.1.dist-info/WHEEL
odoo13_addon_account_invoice_mode_monthly-13.0.1.0.1.dist-info/top_level.txt
odoo13_addon_account_invoice_mode_monthly-13.0.1.0.1.dist-info/RECORD
